[
{"content":{"body":"👋","m.mentions":{},"msgtype":"m.text"},"ts":1784555692847,"senderName":"Chris de Almeida","senderId":"@softwarechris:matrix.org","id":"$PHsXoWe0AM-dgYoGJ7NcUl7rNmQJ7fNbHiosVanrI9I"},
{"content":{"body":"📢 plenary begins in ~1 hr","m.mentions":{},"msgtype":"m.text"},"ts":1784555712657,"senderName":"Chris de Almeida","senderId":"@softwarechris:matrix.org","id":"$wJTgwGMlQHRARQUBL0WBxkHyvy6Hjw-TdNSlVM9KeV0"},
{"content":{"body":"Be careful because Teams seems to default to having the mic on when you join","m.mentions":{},"msgtype":"m.text"},"ts":1784559731275,"senderName":"nicolo-ribaudo","senderId":"@nicolo-ribaudo:matrix.org","id":"$UKFB8BGXawxfrjVRCQw5j_lUPRD63vWCSTeZSsPctIk"},
{"content":{"body":"yeah it does, sorry about the crunching, I was sure i had muted","m.mentions":{},"msgtype":"m.text"},"ts":1784559903174,"senderName":"Aki","senderId":"@akirose:matrix.org","id":"$9DGTIjwooeNVtn22uflP3P20o3nTmnKWCskl37LOVUM"},
{"content":{"body":"29th Sept to 21 Oct is a long meeting!","m.mentions":{},"msgtype":"m.text"},"ts":1784560098898,"senderName":"Michael Ficarra","senderId":"@michaelficarra:matrix.org","id":"$cA8OM01UWodIMJmyeJB8nmpVBfKwvrGqYTU1qN4diuc"},
{"content":{"body":"They did advertise that length already at the last meeting, though.","m.mentions":{},"msgtype":"m.text"},"ts":1784560220830,"senderName":"eemeli","senderId":"@eemeli:mozilla.org","id":"$Ff0Ic1Z1CsCTdL88HbLQZaY3SMN46X-K6lWKklgKMWY"}
]