[
{"content":{"body":"Hey all","m.mentions":{},"msgtype":"m.text"},"ts":1773237402181,"senderName":"Rob Palmer","senderId":"@robpalme:matrix.org","id":"$j2BZRCaunJcpf4kERd4s5jRxHZX8PfU-67W5Z0BF4YI"},
{"content":{"body":"We are starting in two minutes!","m.mentions":{},"msgtype":"m.text"},"ts":1773237425589,"senderName":"Rob Palmer","senderId":"@robpalme:matrix.org","id":"$5nTjF2bTZPZU2gLWilTL30wD-e8MIlcGqdKmjZO0_Gs"},
{"content":{"body":"Reminder: Please add yourself to the attendees section of day two of the notes ","m.mentions":{},"msgtype":"m.text"},"ts":1773237573991,"senderName":"Ashley Claymore","senderId":"@aclaymore:matrix.org","id":"$trgyADMKgcldNRCCEUw-N9CzKRVSxJlWzbFiQQPb2kE"},
{"content":{"body":"LibJS == LibJS right?","m.mentions":{},"msgtype":"m.text"},"ts":1773237985698,"senderName":"Chris de Almeida","senderId":"@softwarechris:matrix.org","id":"$CX0upRf6BynhwRuhkC7s9ohDm9Y_GC2NHOzORCa7MsU"},
{"content":{"body":"* Ladybird == LibJS right?","m.mentions":{},"m.new_content":{"body":"Ladybird == LibJS right?","m.mentions":{},"msgtype":"m.text"},"m.relates_to":{"event_id":"$CX0upRf6BynhwRuhkC7s9ohDm9Y_GC2NHOzORCa7MsU","rel_type":"m.replace"},"msgtype":"m.text"},"ts":1773237991350,"senderName":"Chris de Almeida","senderId":"@softwarechris:matrix.org","id":"$AcOsb3UPmT6I8EoTaeD3uznJ0rKAv2fy1TwU6cdrvMg"},
{"content":{"body":"Ladybird is the browser and LibJS is the JS interpreter","m.mentions":{},"msgtype":"m.text"},"ts":1773238025403,"senderName":"ryzokuken","senderId":"@usharma:igalia.com","id":"$mD3ArWVPRpvSWx4TkMUb5mhUW7OxkZa--cDb--qHhZw"},
{"content":{"body":"https://ladybird.org/posts/adopting-rust/","m.mentions":{},"msgtype":"m.text"},"ts":1773238427970,"senderName":"Ashley Claymore","senderId":"@aclaymore:matrix.org","id":"$byyOTNPsVKotzBQoBoS_NIYoXKuT3SH3jpkizTPQ53o"},
{"content":{"body":"from the perspective of multiple other standards that normatively reference exclusively the regex portion of the standard… can we come back to that question in the future?","m.mentions":{},"msgtype":"m.text"},"ts":1773239506218,"senderName":"Aki","senderId":"@akirose:matrix.org","id":"$KRBdOfwQY4cilf94F7qdJInvdIMB7f5d5JVI6rMzwaQ"},
{"content":{"body":"Reminder that ECMA-414 exists, and functionally exists to lay out all the standards required to implement all of standardised ECMAScript","m.mentions":{},"msgtype":"m.text"},"ts":1773239671616,"senderName":"Aki","senderId":"@akirose:matrix.org","id":"$pABwc2KB5xtzvNhiKB6pMGqdAM5SapW_uD9cETjWT0w"},
{"content":{"body":"a single document that contains all web specs sounds nuts","m.mentions":{},"msgtype":"m.text"},"ts":1773239750344,"senderName":"Michael Ficarra","senderId":"@michaelficarra:matrix.org","id":"$5w4n5uR2PJ2dKhFUbVOaSPATgGNPrUrEmgbogKGVqKc"},
{"content":{"body":"Getting Internal Server Errors on TCQ","m.mentions":{},"msgtype":"m.text"},"ts":1773239809747,"senderName":"waldemar","senderId":"@waldemarh:matrix.org","id":"$IR9u6gf1lXPZGFdX6Fr_jjABOuzQzzKeqeeEP3ppStE"},
{"content":{"body":"ooh but an ECMA-414-style document for the web *eyebrows eyebrows*","format":"org.matrix.custom.html","formatted_body":"ooh but an ECMA-414-style document for the web <em>eyebrows eyebrows</em>","m.mentions":{},"msgtype":"m.text"},"ts":1773239810309,"senderName":"Aki","senderId":"@akirose:matrix.org","id":"$laL58VZ_H2ht6dXimgnyd1Iy1gaUinPlrtjqv4RnKzY"},
{"content":{"body":"ECMA-426 normatively references ECMA-262 machinery: https://tc39.es/ecma426/#sec-MatchSourceMapURL","m.mentions":{"user_ids":["@akirose:matrix.org"]},"m.relates_to":{"m.in_reply_to":{"event_id":"$KRBdOfwQY4cilf94F7qdJInvdIMB7f5d5JVI6rMzwaQ"}},"msgtype":"m.text"},"ts":1773240256913,"senderName":"Richard Gibson","senderId":"@gibson042:matrix.org","id":"$YwMNjlMWoQa1Cs1IdypGBPBjtFx85zQ0lUEIuL-srfo"},
{"content":{"body":"as does 424, and 42…9? maybe? and a bunch outside of Ecma","m.mentions":{},"msgtype":"m.text"},"ts":1773240291862,"senderName":"Aki","senderId":"@akirose:matrix.org","id":"$Jz6CV9YpqkXm1_2tCS4vDFTgshyoRwyvEFzdEZexZTM"},
{"content":{"body":"* ECMA-426 normatively references ECMA-262 regular expression machinery: https://tc39.es/ecma426/#sec-MatchSourceMapURL","m.mentions":{},"m.new_content":{"body":"ECMA-426 normatively references ECMA-262 regular expression machinery: https://tc39.es/ecma426/#sec-MatchSourceMapURL","m.mentions":{"user_ids":["@akirose:matrix.org"]},"msgtype":"m.text"},"m.relates_to":{"event_id":"$YwMNjlMWoQa1Cs1IdypGBPBjtFx85zQ0lUEIuL-srfo","rel_type":"m.replace"},"msgtype":"m.text"},"ts":1773240310848,"senderName":"Richard Gibson","senderId":"@gibson042:matrix.org","id":"$MjZy1_V3DRuTaCOp8XhTGhPCxw36u6dzDW28Ef7Ctxw"},
{"content":{"body":"why? i want it very much","m.mentions":{"user_ids":["@michaelficarra:matrix.org"]},"m.relates_to":{"m.in_reply_to":{"event_id":"$5w4n5uR2PJ2dKhFUbVOaSPATgGNPrUrEmgbogKGVqKc"}},"msgtype":"m.text"},"ts":1773240321862,"senderName":"ljharb","senderId":"@ljharb:matrix.org","id":"$QhTJaceWPeM_QQAx1P3zZtcxM673_jXwvakPsaCY-3s"},
{"content":{"body":"if it's not nuts to put it all in the same app, then it shouldn't be nuts to put it in the same doc :-p","m.mentions":{},"msgtype":"m.text"},"ts":1773240334032,"senderName":"ljharb","senderId":"@ljharb:matrix.org","id":"$-3sLwjFvRTLMqpzEg99Fd__ksMl0X606SJcSE3iaxiw"},
{"content":{"body":"where would you even establish the cutoff? Does it include HTTP? WebSocket? DNS? QUIC?","m.mentions":{},"msgtype":"m.text"},"ts":1773240410352,"senderName":"Richard Gibson","senderId":"@gibson042:matrix.org","id":"$UgTUVLFc4o0olcXvFu3xL2Hg234N4miHVZY5K4nyXmc"},
{"content":{"body":"everything. i want a single document that defines everything a web browser needs to be compliant.","m.mentions":{},"msgtype":"m.text"},"ts":1773240491820,"senderName":"ljharb","senderId":"@ljharb:matrix.org","id":"$UhiX2LzDZIDMHFiUM8WxD8VW1fs4FXWubva8SWfaIFA"},
{"content":{"body":"iow i don't agree with \"you have to draw a line somewhere\" - you can just not draw a line","m.mentions":{},"msgtype":"m.text"},"ts":1773240504357,"senderName":"ljharb","senderId":"@ljharb:matrix.org","id":"$1TylCAFWmehJ7J4kxlI7L1WXlzDi131z7JblzV5H7Gs"},
{"content":{"body":"clarified above, I was specifically referring to other specs referencing ECMA-262 regular expressions","m.mentions":{"user_ids":["@akirose:matrix.org"]},"m.relates_to":{"m.in_reply_to":{"event_id":"$Jz6CV9YpqkXm1_2tCS4vDFTgshyoRwyvEFzdEZexZTM"}},"msgtype":"m.text"},"ts":1773240506479,"senderName":"Richard Gibson","senderId":"@gibson042:matrix.org","id":"$CzcSyTpYHsT5xLaWVEL2rjKHBFAcuyk3D8pXYcVwhVw"},
{"content":{"body":"as was i","m.mentions":{},"msgtype":"m.text"},"ts":1773240515177,"senderName":"Aki","senderId":"@akirose:matrix.org","id":"$_eCmZboxEMLTNQ_lcCAcDbQyfzz8F5DFMRpzbXmUyLQ"},
{"content":{"body":"oh, I didn't see any reference to regular expressions in ECMA-424","m.mentions":{},"msgtype":"m.text"},"ts":1773240534679,"senderName":"Richard Gibson","senderId":"@gibson042:matrix.org","id":"$wmSqktsdAEUaBlGTk6YmG4Z7VS6DEbsFRksUw7FZadQ"},
{"content":{"body":"in that case, good luck to you","m.mentions":{"user_ids":["@ljharb:matrix.org"]},"m.relates_to":{"m.in_reply_to":{"event_id":"$1TylCAFWmehJ7J4kxlI7L1WXlzDi131z7JblzV5H7Gs"}},"msgtype":"m.text"},"ts":1773240543099,"senderName":"Richard Gibson","senderId":"@gibson042:matrix.org","id":"$uh7Jg6puD-CuxvxU7Ch8kqD0RDTvdTPpS62dWUbAV14"},
{"content":{"body":"oh 427 is what i meant","m.mentions":{},"msgtype":"m.text"},"ts":1773240592828,"senderName":"Aki","senderId":"@akirose:matrix.org","id":"$oPjwqe42KQKWtCt-v3SQOjHoZdbbyOr9ukIq7w14y4E"},
{"content":{"body":"too many numbers","m.mentions":{},"msgtype":"m.text"},"ts":1773240598901,"senderName":"Aki","senderId":"@akirose:matrix.org","id":"$tAfWdPVemrdrQYSo2WDyXa4W6QhEDuEfEbOJxHD8ErY"},
{"content":{"body":"the POSIX specification is at https://pubs.opengroup.org/onlinepubs/9799919799/ , and ISO C is https://www.iso.org/standard/82075.html","m.mentions":{},"msgtype":"m.text"},"ts":1773240605048,"senderName":"Richard Gibson","senderId":"@gibson042:matrix.org","id":"$jZqP7emjCbWTcjC_sYXMfCIyFercEzSif22AmBr5A_4"},
{"content":{"body":"It also references a bunch of other stuff, like Call and JSON.parse","m.mentions":{"user_ids":["@gibson042:matrix.org"]},"m.relates_to":{"m.in_reply_to":{"event_id":"$YwMNjlMWoQa1Cs1IdypGBPBjtFx85zQ0lUEIuL-srfo"}},"msgtype":"m.text"},"ts":1773240612767,"senderName":"nicolo-ribaudo","senderId":"@nicolo-ribaudo:matrix.org","id":"$qypaKV7JcOqan3vlW6djlJIr8Cbi_i0dcQdjTongYX8"},
{"content":{"body":"The next Ecma standard will indeed by ECMA-435","m.mentions":{},"msgtype":"m.text"},"ts":1773240698658,"senderName":"Aki","senderId":"@akirose:matrix.org","id":"$2RCidDSAQ_ePyzG1dy9xHhgwFLp3SPXoi5hQ0kAIqaU"},
{"content":{"body":"* The next Ecma standard will indeed be ECMA-435","m.mentions":{},"m.new_content":{"body":"The next Ecma standard will indeed be ECMA-435","m.mentions":{},"msgtype":"m.text"},"m.relates_to":{"event_id":"$2RCidDSAQ_ePyzG1dy9xHhgwFLp3SPXoi5hQ0kAIqaU","rel_type":"m.replace"},"msgtype":"m.text"},"ts":1773240705720,"senderName":"Aki","senderId":"@akirose:matrix.org","id":"$f0FOZBRLmlcU5CCLur-AV7xQssBc5rHGiOawh_zx34k"},
{"content":{"body":"jkup: What does SME mean?","format":"org.matrix.custom.html","formatted_body":"<a href=\"https://matrix.to/#/@jkup:matrix.org\">jkup</a>: What does SME mean?","m.mentions":{"user_ids":["@jkup:matrix.org"]},"msgtype":"m.text"},"ts":1773241420153,"senderName":"nicolo-ribaudo","senderId":"@nicolo-ribaudo:matrix.org","id":"$z9uueicQt756Iwin_m3qG-wHRPA1ZD8jxfWQPtyFoXQ"},
{"content":{"body":"Can I express my unconditional support for advancing Error code property to all stages requested, in case I'm unavailable to do it synchronously?","m.mentions":{},"msgtype":"m.text"},"ts":1773241427375,"senderName":"Zb Tenerowicz (ZTZ/naugtur)","senderId":"@naugtur:matrix.org","id":"$OJBHmQ7pZh_kVU5G0pFJX5_n_QL-lmcmh7g9t-BB_KE"},
{"content":{"body":"Subject Matter Expert","m.mentions":{"user_ids":["@nicolo-ribaudo:matrix.org"]},"m.relates_to":{"m.in_reply_to":{"event_id":"$z9uueicQt756Iwin_m3qG-wHRPA1ZD8jxfWQPtyFoXQ"}},"msgtype":"m.text"},"ts":1773241450812,"senderName":"Richard Gibson","senderId":"@gibson042:matrix.org","id":"$ZXaANp63bCiay6AYWyHkpzPVUyj6y0eH1H8fmCD95OM"},
{"content":{"body":"sorry","m.mentions":{},"msgtype":"m.text"},"ts":1773241485226,"senderName":"jkup","senderId":"@jkup:matrix.org","id":"$3_vH3HtoGCWbiSshNGDmZXsnoiYtsRG2ADwyGcDewN4"},
{"content":{"body":"I just like the idea a lot of trying to make sure we have a regex/intl/temporal person always on the editor group","m.mentions":{},"msgtype":"m.text"},"ts":1773241499822,"senderName":"jkup","senderId":"@jkup:matrix.org","id":"$uUI6R9yisJsMenzxbc-7-VhPYIHEXQFl-mnc11CeZKs"},
{"content":{"body":"as another example: we often run into ambiguities and as editors need to figure out the committee-ordained normative behaviour so we can make editorial clarifications","m.mentions":{},"msgtype":"m.text"},"ts":1773241516539,"senderName":"Michael Ficarra","senderId":"@michaelficarra:matrix.org","id":"$ufdayl8-Qg-Qm8xEl6tBSaXHbQZ7c38E3RLTHOteYtc"},
{"content":{"body":"ty :)","m.mentions":{},"m.relates_to":{"event_id":"$ZXaANp63bCiay6AYWyHkpzPVUyj6y0eH1H8fmCD95OM","is_falling_back":true,"m.in_reply_to":{"event_id":"$ZXaANp63bCiay6AYWyHkpzPVUyj6y0eH1H8fmCD95OM"},"rel_type":"m.thread"},"msgtype":"m.text"},"ts":1773241518192,"senderName":"nicolo-ribaudo","senderId":"@nicolo-ribaudo:matrix.org","id":"$ann6oVycUSCEu3CrnaqTSJ4ifoKVoLo_FnEtorsFCDw"},
{"content":{"body":"I think there is general ambiguity around when to task group, when to just have a subgroup meeting, when to just have an editor who is a subject matter expert","m.mentions":{},"msgtype":"m.text"},"ts":1773241598267,"senderName":"jkup","senderId":"@jkup:matrix.org","id":"$9U5bEB_FXHMUi3Ptu61D97sL-hkra0C2c1D7GHIdCYw"},
{"content":{"body":"I wanna say 8½ years since stage 2","m.mentions":{},"msgtype":"m.text"},"ts":1773242193646,"senderName":"Aki","senderId":"@akirose:matrix.org","id":"$2BRybskq-McQCzYDBgTm6UMMd_1FctmGRRj2Iv0dyL0"},
{"content":{"body":"The \"it's about time\" jokes write themselves","msgtype":"m.text"},"ts":1773242227237,"senderName":"James M Snell","senderId":"@jasnell:matrix.org","id":"$CgTZ-ubLwa6ANuFJQKp_HPI1hZmFqeWEB8KZvBAwiuU"},
{"content":{"body":"(which also means i've been involved with TC39 for 8½ years and that doesn't seem right)","m.mentions":{},"msgtype":"m.text"},"ts":1773242232997,"senderName":"Aki","senderId":"@akirose:matrix.org","id":"$bz_maAko3u1w1rRs0XBAkkPWEkXw6X8Uzw_4fBY3PjY"},
{"content":{"body":"there's a lot of things like that; big ones that come to mind are unicode, parsing, atomics, and module machinery","m.mentions":{"user_ids":["@jkup:matrix.org"]},"m.relates_to":{"m.in_reply_to":{"event_id":"$uUI6R9yisJsMenzxbc-7-VhPYIHEXQFl-mnc11CeZKs"}},"msgtype":"m.text"},"ts":1773242255771,"senderName":"bakkot","senderId":"@bakkot:matrix.org","id":"$TX6dqqY_MlyNvP66o-KdaniElq9ZP66mQRzcdBlTcLw"},
{"content":{"body":"Incredible work by the champion group and the committee as a whole!","m.mentions":{},"msgtype":"m.text"},"ts":1773242263621,"senderName":"Ashley Claymore","senderId":"@aclaymore:matrix.org","id":"$d8QV9e9ck9GUWD8d6082Ej2fLZHHylKFdDLHIKOAjNc"},
{"content":{"body":"prior editor group did not have great coverage for module machinery","m.mentions":{},"msgtype":"m.text"},"ts":1773242273742,"senderName":"bakkot","senderId":"@bakkot:matrix.org","id":"$kYwEtAKiYEeB43RJm3LXIY_vI3CR_nJxcdB6apCRXOM"},
{"content":{"body":"Very happy for Temporal being stage 4 now!","m.mentions":{},"msgtype":"m.text"},"ts":1773242280276,"senderName":"Shark","senderId":"@sharktheone:matrix.org","id":"$DvcdXs5VjLIUZXho_drNyNU1sS6uPSbmzt3fVc_yGJQ"}
]