[
{"content":{"body":"why is it so hard to find the invites to these matrix channels or the space? The *only* place I can seem to find them mentioned at all is https://github.com/tc39/how-we-work/blob/a64ad4bf2276063bfd268d50d5fbe393369b9fff/matrix-guide.md, a somewhat obscure markdown file which also seems worded more towards *exclusively* TC39 delegates and not the general public","format":"org.matrix.custom.html","formatted_body":"why is it so hard to find the invites to these matrix channels or the space? The <em>only</em> place I can seem to find them mentioned at all is https://github.com/tc39/how-we-work/blob/a64ad4bf2276063bfd268d50d5fbe393369b9fff/matrix-guide.md, a somewhat obscure markdown file which also seems worded more towards <em>exclusively</em> TC39 delegates and not the general public","msgtype":"m.text"},"ts":1685263390854,"senderName":"voidhedron","senderId":"@voidhedron:matrix.org","id":"$SyesIZUwGGBjF2ZBXEsvif3PffLystKT51smm-o-u40"},
{"content":{"body":"not even at the bottom of https://tc39.es/ in the \"Connect\" section is the existence of the matrix channels acknowledged, why is this?","msgtype":"m.text"},"ts":1685263484374,"senderName":"voidhedron","senderId":"@voidhedron:matrix.org","id":"$mTQ7wI4C1AawqHdoftDWSPPz_ij4kMj8ytJp8mW1JY0"}
]