[
{"content":{"body":"hi! I'm wondering what all the implementations are doing in their test262 runs regarding JSON modules - it's a stage 3 proposal but IIUC it requires the syntax from import assertions, which was bumped back to stage 2 in the last meeting","msgtype":"m.text","org.matrix.msc1767.text":"hi! I'm wondering what all the implementations are doing in their test262 runs regarding JSON modules - it's a stage 3 proposal but IIUC it requires the syntax from import assertions, which was bumped back to stage 2 in the last meeting"},"ts":1676486388223,"senderName":"ptomato","senderId":"@pchimento:igalia.com","id":"$VZlQ2ZEhG2z5bGbAerMjxlvU2mSsT1lVfuBdeYHUc8c"}
]